setup.py
brynq_sdk_elastic/__init__.py
brynq_sdk_elastic/elastic.py
brynq_sdk_elastic.egg-info/PKG-INFO
brynq_sdk_elastic.egg-info/SOURCES.txt
brynq_sdk_elastic.egg-info/dependency_links.txt
brynq_sdk_elastic.egg-info/not-zip-safe
brynq_sdk_elastic.egg-info/requires.txt
brynq_sdk_elastic.egg-info/top_level.txt