Metadata-Version: 1.0
Name: brynq-sdk-elastic
Version: 3.0.4
Summary: elastic wrapper from BrynQ
Home-page: UNKNOWN
Author: BrynQ
Author-email: support@brynq.com
License: BrynQ License
Platform: UNKNOWN
